[
  {
    "id": "banner-welcome",
    "title": "Welcome to Blink Box",
    "subtitle": "Fresh Groceries Delivered in Minutes",
    "imageUrl": "/static/banners/welcome.png",
    "ctaText": "Start Shopping",
    "clickDestination": "grocery",
    "isActive": true,
    "sortOrder": 1,
    "startDate": null,
    "endDate": null,
    "campaignType": "welcome",
    "clicks": 0,
    "createdAt": "2026-06-12T00:00:00.000Z"
  },
  {
    "id": "banner-summer",
    "title": "Summer Mega Sale",
    "subtitle": "Up to 50% OFF on Seasonal Essentials",
    "imageUrl": "/static/banners/summer.png",
    "ctaText": "Shop Summer Deals",
    "clickDestination": "grocery",
    "isActive": true,
    "sortOrder": 2,
    "startDate": null,
    "endDate": null,
    "campaignType": "summer",
    "clicks": 1,
    "createdAt": "2026-06-12T00:00:00.000Z"
  },
  {
    "id": "banner-fruits",
    "title": "Farm Fresh Fruits",
    "subtitle": "Picked Fresh, Delivered Fast",
    "imageUrl": "/static/banners/fruits.png",
    "ctaText": "Explore Collection",
    "clickDestination": "fruits",
    "isActive": true,
    "sortOrder": 3,
    "startDate": null,
    "endDate": null,
    "campaignType": "fruits",
    "clicks": 1,
    "createdAt": "2026-06-12T00:00:00.000Z"
  },
  {
    "id": "banner-vegetables",
    "title": "Daily Fresh Vegetables",
    "subtitle": "Healthy Choices for Every Meal",
    "imageUrl": "/static/banners/vegetables.png",
    "ctaText": "Order Now",
    "clickDestination": "vegetables",
    "isActive": true,
    "sortOrder": 4,
    "startDate": null,
    "endDate": null,
    "campaignType": "vegetables",
    "clicks": 0,
    "createdAt": "2026-06-12T00:00:00.000Z"
  },
  {
    "id": "banner-savings",
    "title": "Save More Every Day",
    "subtitle": "Exclusive Grocery Deals",
    "imageUrl": "/static/banners/savings.png",
    "ctaText": "View Offers",
    "clickDestination": "grocery",
    "isActive": true,
    "sortOrder": 5,
    "startDate": null,
    "endDate": null,
    "campaignType": "savings",
    "clicks": 0,
    "createdAt": "2026-06-12T00:00:00.000Z"
  },
  {
    "id": "banner-dairy",
    "title": "Morning Essentials",
    "subtitle": "Fresh Breakfast Delivered",
    "imageUrl": "/static/banners/dairy.png",
    "ctaText": "Buy Now",
    "clickDestination": "dairy",
    "isActive": true,
    "sortOrder": 6,
    "startDate": null,
    "endDate": null,
    "campaignType": "dairy",
    "clicks": 0,
    "createdAt": "2026-06-12T00:00:00.000Z"
  },
  {
    "id": "banner-weekend",
    "title": "Weekend Flash Sale",
    "subtitle": "Flat 50% OFF on Selected Products",
    "imageUrl": "/static/banners/weekend.png",
    "ctaText": "Grab the Deal",
    "clickDestination": "grocery",
    "isActive": true,
    "sortOrder": 7,
    "startDate": null,
    "endDate": null,
    "campaignType": "weekend",
    "clicks": 0,
    "createdAt": "2026-06-12T00:00:00.000Z"
  },
  {
    "id": "banner-festival",
    "title": "Festival Specials",
    "subtitle": "Celebrate with Premium Essentials",
    "imageUrl": "/static/banners/festival.png",
    "ctaText": "Shop Now",
    "clickDestination": "grocery",
    "isActive": true,
    "sortOrder": 8,
    "startDate": null,
    "endDate": null,
    "campaignType": "festival",
    "clicks": 0,
    "createdAt": "2026-06-12T00:00:00.000Z"
  }
]